AUTHORS.md
CONTRIBUTING.md
LICENSE
README.md
cbdf_api/__init__.py
cbdf_api/architecture.py
cbdf_api/augmentation.py
cbdf_api/callback.py
cbdf_api/generate_templates.py
cbdf_api/initializer.py
cbdf_api/interface.py
cbdf_api/loss.py
cbdf_api/metric.py
cbdf_api/optimizer.py
cbdf_api/postprocessor.py
cbdf_api/preprocessor.py
cbdf_api/utils.py
cbdf_api-3.0.3.dist-info/entry_points.txt
cbdf_api-3.0.3.dist-info/LICENSE
cbdf_api-3.0.3.dist-info/WHEEL
cbdf_api-3.0.3.dist-info/METADATA
cbdf_api-3.0.3.dist-info/RECORD
